{
  "$schema": "https://ui.shadcn.com/schema/registry.json",
  "name": "UI Library",
  "homepage": "https://sogeman.github.io/hen-ui-library",
  "items": [
    {
      "name": "theme",
      "type": "registry:style",
      "description": "Color theme with CSS custom properties for light and dark modes",
      "registryDependencies": [],
      "dependencies": [],
      "files": [
        {
          "path": "src/registry/new-york/styles/theme.css",
          "type": "registry:style",
          "target": "styles/theme.css"
        }
      ],
      "tailwind": {
        "config": {
          "theme": {
            "extend": {
              "colors": {
                "border": "var(--border)",
                "input": "var(--input)",
                "ring": "var(--ring)",
                "background": "var(--background)",
                "foreground": "var(--foreground)",
                "primary": {
                  "DEFAULT": "var(--primary)",
                  "foreground": "var(--primary-foreground)"
                },
                "secondary": {
                  "DEFAULT": "var(--secondary)",
                  "foreground": "var(--secondary-foreground)"
                },
                "destructive": {
                  "DEFAULT": "var(--destructive)",
                  "foreground": "var(--destructive-foreground)"
                },
                "muted": {
                  "DEFAULT": "var(--muted)",
                  "foreground": "var(--muted-foreground)"
                },
                "accent": {
                  "DEFAULT": "var(--accent)",
                  "foreground": "var(--accent-foreground)"
                },
                "card": {
                  "DEFAULT": "var(--card)",
                  "foreground": "var(--card-foreground)"
                },
                "popover": {
                  "DEFAULT": "var(--popover)",
                  "foreground": "var(--popover-foreground)"
                },
                "sidebar": {
                  "DEFAULT": "var(--sidebar)",
                  "foreground": "var(--sidebar-foreground)",
                  "primary": "var(--sidebar-primary)",
                  "primary-foreground": "var(--sidebar-primary-foreground)",
                  "accent": "var(--sidebar-accent)",
                  "accent-foreground": "var(--sidebar-accent-foreground)",
                  "border": "var(--sidebar-border)",
                  "ring": "var(--sidebar-ring)"
                }
              },
              "borderRadius": {
                "lg": "var(--radius)",
                "md": "calc(var(--radius) - 2px)",
                "sm": "calc(var(--radius) - 4px)"
              }
            }
          }
        }
      }
    },
    {
      "name": "badge",
      "type": "registry:component",
      "description": "A badge component for status indicators",
      "registryDependencies": [],
      "dependencies": [],
      "files": [
        {
          "path": "src/registry/new-york/components/badge/badge.tsx",
          "type": "registry:ui"
        }
      ]
    },
    {
      "name": "button",
      "type": "registry:component",
      "description": "A customizable button component with variants and sizes",
      "registryDependencies": [],
      "dependencies": [],
      "files": [
        {
          "path": "src/registry/new-york/components/button/button.tsx",
          "type": "registry:ui"
        }
      ]
    },
    {
      "name": "card",
      "type": "registry:component",
      "description": "A card component for displaying content",
      "registryDependencies": [],
      "dependencies": [],
      "files": [
        {
          "path": "src/registry/new-york/components/card/card.tsx",
          "type": "registry:ui",
          "target": "components/ui/card.tsx"
        },
        {
          "path": "src/registry/new-york/components/card/components/card-header.tsx",
          "type": "registry:ui",
          "target": "components/ui/card/components/card-header.tsx"
        },
        {
          "path": "src/registry/new-york/components/card/components/card-title.tsx",
          "type": "registry:ui",
          "target": "components/ui/card/components/card-title.tsx"
        },
        {
          "path": "src/registry/new-york/components/card/components/card-description.tsx",
          "type": "registry:ui",
          "target": "components/ui/card/components/card-description.tsx"
        },
        {
          "path": "src/registry/new-york/components/card/components/card-content.tsx",
          "type": "registry:ui",
          "target": "components/ui/card/components/card-content.tsx"
        },
        {
          "path": "src/registry/new-york/components/card/components/card-footer.tsx",
          "type": "registry:ui",
          "target": "components/ui/card/components/card-footer.tsx"
        }
      ]
    },
    {
      "name": "input",
      "type": "registry:component",
      "description": "An input component with label and error states",
      "registryDependencies": [],
      "dependencies": [],
      "files": [
        {
          "path": "src/registry/new-york/components/input/input.tsx",
          "type": "registry:ui"
        }
      ]
    },
    {
      "name": "grid",
      "type": "registry:component",
      "description": "A flexible grid layout component with responsive columns and gaps",
      "registryDependencies": [],
      "dependencies": [],
      "files": [
        {
          "path": "src/registry/new-york/components/grid/grid.tsx",
          "type": "registry:ui"
        }
      ]
    },
    {
      "name": "alert",
      "type": "registry:component",
      "description": "Display alert messages with different variants for info, success, warning, and errors",
      "registryDependencies": [],
      "dependencies": [],
      "files": [
        {
          "path": "src/registry/new-york/components/alert/alert.tsx",
          "type": "registry:ui",
          "target": "components/ui/alert.tsx"
        },
        {
          "path": "src/registry/new-york/components/alert/components/alert-title.tsx",
          "type": "registry:ui",
          "target": "components/ui/alert/components/alert-title.tsx"
        },
        {
          "path": "src/registry/new-york/components/alert/components/alert-description.tsx",
          "type": "registry:ui",
          "target": "components/ui/alert/components/alert-description.tsx"
        }
      ]
    },
    {
      "name": "checkbox",
      "type": "registry:component",
      "description": "A checkbox input component with optional label support",
      "registryDependencies": [],
      "dependencies": [],
      "files": [
        {
          "path": "src/registry/new-york/components/checkbox/checkbox.tsx",
          "type": "registry:ui"
        }
      ]
    },
    {
      "name": "switch",
      "type": "registry:component",
      "description": "A toggle switch component for on/off states with multiple sizes",
      "registryDependencies": [],
      "dependencies": [],
      "files": [
        {
          "path": "src/registry/new-york/components/switch/switch.tsx",
          "type": "registry:ui"
        }
      ]
    },
    {
      "name": "avatar",
      "type": "registry:component",
      "description": "Display user avatars with image support and fallback to initials",
      "registryDependencies": [],
      "dependencies": [],
      "files": [
        {
          "path": "src/registry/new-york/components/avatar/avatar.tsx",
          "type": "registry:ui"
        }
      ]
    },
    {
      "name": "select",
      "type": "registry:component",
      "description": "A dropdown select component for choosing from a list of options",
      "registryDependencies": [],
      "dependencies": [],
      "files": [
        {
          "path": "src/registry/new-york/components/select/select.tsx",
          "type": "registry:ui"
        }
      ]
    },
    {
      "name": "menu",
      "type": "registry:component",
      "description": "A dropdown menu component with customizable positioning and items",
      "registryDependencies": [],
      "dependencies": [],
      "files": [
        {
          "path": "src/registry/new-york/components/menu/menu.tsx",
          "type": "registry:ui"
        }
      ]
    },
    {
      "name": "textarea",
      "type": "registry:component",
      "description": "A textarea component with label and error states for multi-line text input",
      "registryDependencies": [],
      "dependencies": [],
      "files": [
        {
          "path": "src/registry/new-york/components/textarea/textarea.tsx",
          "type": "registry:ui"
        }
      ]
    }
  ]
}
